[
	{
		"name": "University of Sheffield",
		"image": "TUOS.png",
		"url": "../Sheffield"
	},
	{
		"name": "University of Oxford",
		"image": "oxford.png",
		"url": "http://www.oerc.ox.ac.uk/research-scientific-computing/scientific-computing"
	},
	{
		"name": "University of Cambridge",
		"image": "cambridge.jpeg",
		"url": "http://www.hpc.cam.ac.uk/services/wilkes"
	},
	{
		"name": "University of Manchester",
		"image": "manchester.png",
		"url": "http://wiki.rac.manchester.ac.uk/community/GPU/"
	},	
	{
		"name": "Queen's University Belfast",
		"image": "queens_belfast.jpg",
		"url": "http://www.qub.ac.uk/research-centres/HPDC/"
	},	
	{
		"name": "Imperial College London",
		"image": "imperial.png",
		"url": "http://www.imperial.ac.uk/computational-methods"
	},	
	{
		"name": "UCL",
		"image": "ucl.jpg",
		"url": "https://www.ucl.ac.uk/research-it-services/research-software-development/programming-hub/gpu-forum"
	},	
	{
		"name": "University of Bristol",
		"image": "bristol.jpg",
		"url": "http://www.bristol.ac.uk/brissynbio/equipment/hpc/"
	},	
	{
		"name": "University of Durham",
		"image": "durham.png",
		"url": "https://www.dur.ac.uk/iarc/nvidiacuda/"
	},	
	{
		"name": "STFC Daresbury",
		"image": "stfc.png",
		"url": "http://www.stfc.ac.uk/about-us/where-we-work/rutherford-appleton-laboratory/research-infrastructure-group-rig/"
	},	
	{
		"name": "Lancaster University",
		"image": "lancaster.png",
		"url": "http://www.lancaster.ac.uk/iss/services/hec/"
	},	
	{
		"name": "EPCC Edinburgh",
		"image": "epcc.jpg",
		"url": "https://www.epcc.ed.ac.uk/facilities/demand-computing/gpu"
	},	
]